cspip/__init__.py
cspip/jixnprint.py
cspip-1.0.dist-info/METADATA
cspip-1.0.dist-info/WHEEL
cspip-1.0.dist-info/top_level.txt
cspip-1.0.dist-info/RECORD
