Metadata-Version: 2.1
Name: cspip
Version: 1.0
Summary: 这只是一个测试
Home-page: UNKNOWN
Author: jixn
Author-email: jixn@foxmail.com
License: UNKNOWN
Platform: UNKNOWN
Classifier: Programming Language :: Python :: 3
Classifier: License :: OSI Approved :: MIT License
Classifier: Operating System :: OS Independent
Requires-Python: >=3.7
Requires-Dist: requests
